Mongodb34ZhongwenWendang201756/README.md
Mongodb34ZhongwenWendang201756/__init__.py
Mongodb34ZhongwenWendang201756/__main__.py
Mongodb34ZhongwenWendang201756/file.epub
Mongodb34ZhongwenWendang201756/index.html
Mongodb34ZhongwenWendang201756/css/__init__.py
Mongodb34ZhongwenWendang201756/css/annotations.css
Mongodb34ZhongwenWendang201756/css/main.css
Mongodb34ZhongwenWendang201756/css/normalize.css
Mongodb34ZhongwenWendang201756/css/popup.css
Mongodb34ZhongwenWendang201756/font/__init__.py
Mongodb34ZhongwenWendang201756/font/fontello.eot
Mongodb34ZhongwenWendang201756/font/fontello.svg
Mongodb34ZhongwenWendang201756/font/fontello.ttf
Mongodb34ZhongwenWendang201756/font/fontello.woff
Mongodb34ZhongwenWendang201756/img/__init__.py
Mongodb34ZhongwenWendang201756/img/annotator-glyph-sprite.png
Mongodb34ZhongwenWendang201756/img/annotator-icon-sprite.png
Mongodb34ZhongwenWendang201756/img/apple-touch-icon.png
Mongodb34ZhongwenWendang201756/img/cancelfullscreen.png
Mongodb34ZhongwenWendang201756/img/close.png
Mongodb34ZhongwenWendang201756/img/fullscreen.png
Mongodb34ZhongwenWendang201756/img/loader.gif
Mongodb34ZhongwenWendang201756/img/menu-icon.png
Mongodb34ZhongwenWendang201756/img/save.png
Mongodb34ZhongwenWendang201756/img/saved.png
Mongodb34ZhongwenWendang201756/img/settings-s.png
Mongodb34ZhongwenWendang201756/img/settings.png
Mongodb34ZhongwenWendang201756/img/star.png
Mongodb34ZhongwenWendang201756/js/__init__.py
Mongodb34ZhongwenWendang201756/js/epub.js
Mongodb34ZhongwenWendang201756/js/epub.min.js
Mongodb34ZhongwenWendang201756/js/epub.min.map
Mongodb34ZhongwenWendang201756/js/hooks.min.js
Mongodb34ZhongwenWendang201756/js/hooks.min.map
Mongodb34ZhongwenWendang201756/js/reader.js
Mongodb34ZhongwenWendang201756/js/reader.js.map
Mongodb34ZhongwenWendang201756/js/reader.min.js
Mongodb34ZhongwenWendang201756/js/reader.min.map
Mongodb34ZhongwenWendang201756/js/hooks/__init__.py
Mongodb34ZhongwenWendang201756/js/hooks/extensions/__init__.py
mongodb_3_4_zhongwen_wendang_2017_5_6-2024.3.2.0.dist-info/METADATA
mongodb_3_4_zhongwen_wendang_2017_5_6-2024.3.2.0.dist-info/WHEEL
mongodb_3_4_zhongwen_wendang_2017_5_6-2024.3.2.0.dist-info/entry_points.txt
mongodb_3_4_zhongwen_wendang_2017_5_6-2024.3.2.0.dist-info/top_level.txt
mongodb_3_4_zhongwen_wendang_2017_5_6-2024.3.2.0.dist-info/RECORD
